fancy_printer-0.1.0.dist-info/METADATA
fancy_printer-0.1.0.dist-info/WHEEL
fancy_printer/__init__.py
fancy_printer-0.1.0.dist-info/RECORD
