Metadata-Version: 2.1
Name: fancy_printer
Version: 0.1.0
Summary: A fancy print function for Python
Author-Email: Yanli <mail@yanli.one>
License: Apache-2.0
Requires-Python: >=3.8
